ruckus/__init__.py
ruckus/base.py
ruckus/convolution.py
ruckus/cv_wrappers.py
ruckus/embedding.py
ruckus/sampling.py
ruckus/scoring.py
ruckus/utils.py
ruckus-0.0.8.dist-info/LICENSE
ruckus-0.0.8.dist-info/METADATA
ruckus-0.0.8.dist-info/WHEEL
ruckus-0.0.8.dist-info/top_level.txt
ruckus-0.0.8.dist-info/RECORD
