Metadata-Version: 2.1
Name: ruckus
Version: 0.0.8
Summary: RKHS networks with python and scikit-learn
Home-page: UNKNOWN
Author: Samuel Loomis
Author-email: sloomis@ucdavis.edu
License: MIT
Platform: UNKNOWN
Classifier: Development Status :: 3 - Alpha
Classifier: Intended Audience :: Science/Research
Classifier: Intended Audience :: Developers
Classifier: Topic :: Scientific/Engineering
Classifier: Topic :: Software Development
Classifier: License :: OSI Approved :: MIT License
Classifier: Programming Language :: Python :: 3
Classifier: Programming Language :: Python :: 3.6
Classifier: Programming Language :: Python :: 3.7
Classifier: Programming Language :: Python :: 3.8
Classifier: Programming Language :: Python :: 3.9
License-File: LICENSE
Requires-Dist: numpy (>=1.20.1)
Requires-Dist: scipy (>=1.7.0)
Requires-Dist: scikit-learn (>=1.0.1)
